brunner/__init__.py
brunner/client.py
brunner/py.typed
brunner-1.8.0.dist-info/METADATA
brunner-1.8.0.dist-info/WHEEL
brunner-1.8.0.dist-info/RECORD
