Metadata-Version: 2.1
Name: brunner
Version: 1.8.0
Summary: A client library for accessing Brunner server wrapping the Brunner client API
Home-page: https://windmill.dev
License: Apache-2.0
Author: Burak Akça
Author-email: burak.akca834@gmail.com
Requires-Python: >=3.7,<4.0
Classifier: License :: OSI Approved :: Apache Software License
Classifier: Programming Language :: Python :: 3
Classifier: Programming Language :: Python :: 3.7
Classifier: Programming Language :: Python :: 3.8
Classifier: Programming Language :: Python :: 3.9
Classifier: Programming Language :: Python :: 3.10
Classifier: Programming Language :: Python :: 3.11
Classifier: Programming Language :: Python :: 3.12
Requires-Dist: httpx (>=0.24,<0.25)
Project-URL: Documentation, https://windmill.dev
